LICENSE
LICENSE-APACHE
MANIFEST.in
NOTICE
README.rst
bench.png
pyproject.toml
setup.py
immutables/__init__.py
immutables/_map.c
immutables/_map.h
immutables/_map.pyi
immutables/_protocols.py
immutables/_testutils.py
immutables/_version.py
immutables/map.py
immutables/py.typed
immutables/pythoncapi_compat.h
mvaled_immutables.egg-info/PKG-INFO
mvaled_immutables.egg-info/SOURCES.txt
mvaled_immutables.egg-info/dependency_links.txt
mvaled_immutables.egg-info/requires.txt
mvaled_immutables.egg-info/top_level.txt
tests/__init__.py
tests/conftest.py
tests/test_issue24.py
tests/test_map.py
tests/test_mypy.py
tests/test_none_keys.py