Metadata-Version: 2.1
Name: mvaled-immutables
Version: 0.17.dev0
Summary: Immutable Collections
Home-page: https://github.com/MagicStack/immutables
Author: MagicStack Inc
Author-email: hello@magic.io
License: Apache License, Version 2.0
Platform: UNKNOWN
Classifier: License :: OSI Approved :: Apache Software License
Classifier: Intended Audience :: Developers
Classifier: Programming Language :: Python :: 3 :: Only
Classifier: Programming Language :: Python :: 3.6
Classifier: Programming Language :: Python :: 3.7
Classifier: Programming Language :: Python :: 3.8
Classifier: Programming Language :: Python :: 3.9
Classifier: Programming Language :: Python :: 3.10
Classifier: Operating System :: POSIX
Classifier: Operating System :: MacOS :: MacOS X
Classifier: Operating System :: Microsoft :: Windows
Provides: immutables
Requires-Python: >=3.6
Provides-Extra: test
License-File: LICENSE
License-File: LICENSE-APACHE
License-File: NOTICE
